dialectid/__init__.py
dialectid/model.py
dialectid/utils.py
dialectid/data/emojis.json.gz
dialectid/tests/__init__.py
dialectid/tests/test_model.py
dialectid/tests/test_utils.py
dialectid-0.2.0.dist-info/licenses/LICENSE
dialectid-0.2.0.dist-info/METADATA
dialectid-0.2.0.dist-info/WHEEL
dialectid-0.2.0.dist-info/top_level.txt
dialectid-0.2.0.dist-info/RECORD
