Metadata-Version: 2.4
Name: dialectid
Version: 0.2.0
Summary: Set of algorithms to detect the dialect of a given text
Project-URL: Homepage, https://ingeotec.github.io/dialectid
Project-URL: Repository, https://github.com/INGEOTEC/dialectid
Project-URL: Issues, https://github.com/INGEOTEC/dialectid/issues
Classifier: Development Status :: 3 - Alpha
Classifier: Environment :: Console
Classifier: Intended Audience :: Developers
Classifier: Intended Audience :: Information Technology
Classifier: Intended Audience :: Science/Research
Classifier: License :: OSI Approved :: MIT License
Classifier: Operating System :: OS Independent
Classifier: Programming Language :: Python
Classifier: Topic :: Scientific/Engineering :: Artificial Intelligence
License-File: LICENSE
Requires-Dist: numpy
Requires-Dist: scikit-learn>=1.3.0
Requires-Dist: microtc
Requires-Dist: EncExp
Dynamic: license-file
